docs/Makefile
docs/README.md
docs/make.bat
docs/requirements-docs.txt
docs/source/conf.py
docs/source/index.rst
docs/source/_static/custom.css
docs/source/_templates/layout.html
et_engine/__init__.py
et_engine/batches.py
et_engine/clients.py
et_engine/engine.py
et_engine/filesystems.py
et_engine/tools.py
et_engine-0.0.1.dist-info/LICENSE
et_engine-0.0.1.dist-info/METADATA
et_engine-0.0.1.dist-info/WHEEL
et_engine-0.0.1.dist-info/top_level.txt
et_engine-0.0.1.dist-info/RECORD
