Metadata-Version: 2.1
Name: et_engine
Version: 0.0.1
Summary: The official Python SDK for the ET Engine
Author-email: "Exploration Technologies, Inc." <info@exploretech.ai>
License: 
Keywords: api,exploretech
Requires-Python: >=3.11.9
License-File: LICENSE
Requires-Dist: requests
Requires-Dist: aiohttp
Requires-Dist: aiofiles
Requires-Dist: tqdm
Requires-Dist: et_engine_core>=0.0.1
